qork/__init__.py
qork/ask.py
qork/config.py
qork/main.py
qork/session.py
qork/utils.py
qork-0.1.0.dist-info/METADATA
qork-0.1.0.dist-info/WHEEL
qork-0.1.0.dist-info/entry_points.txt
qork-0.1.0.dist-info/top_level.txt
qork-0.1.0.dist-info/RECORD
