Metadata-Version: 2.4
Name: qork
Version: 0.1.0
Summary: A simple CLI for interacting with OpenAI models.
Author-email: Zubin Aysola <zubinpersonalemail@email.com>
Classifier: Programming Language :: Python :: 3
Classifier: License :: OSI Approved :: MIT License
Classifier: Operating System :: OS Independent
Requires-Python: >=3.7
Requires-Dist: openai
Requires-Dist: rich
Requires-Dist: typer
